Metadata-Version: 2.1
Name: ftw.tokenauth
Version: 1.2.1
Summary: Token Authentication for Plone
Home-page: https://github.com/4teamwork/ftw.tokenauth
Author: 4teamwork AG
Author-email: mailto:info@4teamwork.ch
License: GPL2
Keywords: token authentication plone oauth2 jwt
Platform: UNKNOWN
Classifier: Environment :: Web Environment
Classifier: Framework :: Plone
Classifier: Framework :: Plone :: 4.3
Classifier: Intended Audience :: Developers
Classifier: License :: OSI Approved :: GNU General Public License (GPL)
Classifier: Programming Language :: Python
Classifier: Topic :: Software Development :: Libraries :: Python Modules
Provides-Extra: tests
